{"note":"This file is an internal implementation detail to speed up HTML report generation. Its format can change at any time. You might be looking for the JSON report: https://coverage.rtfd.io/cmd.html#cmd-json","format":5,"version":"7.14.3","globals":"8a574d77bc7d27f6c016defbecf9fa1c","files":{"z_437a7f688279b88f___init___py":{"hash":"0fcf488df86e5a3237ebac126b51aa2d","index":{"url":"z_437a7f688279b88f___init___py.html","file":"src/downbeat/__init__.py","description":"","nums":{"precision":0,"n_files":1,"n_statements":1,"n_excluded":0,"n_missing":0,"n_branches":0,"n_partial_branches":0,"n_missing_branches":0}}},"z_1ef4ac64ffe2aff1___main___py":{"hash":"495d4fae77b01f2ef3f89e17ffde4af8","index":{"url":"z_1ef4ac64ffe2aff1___main___py.html","file":"src/downbeat/cli/__main__.py","description":"","nums":{"precision":0,"n_files":1,"n_statements":118,"n_excluded":0,"n_missing":3,"n_branches":0,"n_partial_branches":0,"n_missing_branches":0}}},"z_5011eddb56125a73_init_cmd_py":{"hash":"8ca0707e9f38df4aafde6df61252b50c","index":{"url":"z_5011eddb56125a73_init_cmd_py.html","file":"src/downbeat/cli/commands/init_cmd.py","description":"","nums":{"precision":0,"n_files":1,"n_statements":293,"n_excluded":0,"n_missing":17,"n_branches":0,"n_partial_branches":0,"n_missing_branches":0}}},"z_5011eddb56125a73_relay_cmds_py":{"hash":"5fd0b6bc42e39247b051627f437ee219","index":{"url":"z_5011eddb56125a73_relay_cmds_py.html","file":"src/downbeat/cli/commands/relay_cmds.py","description":"","nums":{"precision":0,"n_files":1,"n_statements":231,"n_excluded":0,"n_missing":60,"n_branches":0,"n_partial_branches":0,"n_missing_branches":0}}},"z_52b7be57e2e7492a_errors_py":{"hash":"b1200d16d7befccfd05757ef9f08dfa5","index":{"url":"z_52b7be57e2e7492a_errors_py.html","file":"src/downbeat/core/errors.py","description":"","nums":{"precision":0,"n_files":1,"n_statements":7,"n_excluded":0,"n_missing":0,"n_branches":0,"n_partial_branches":0,"n_missing_branches":0}}},"z_52b7be57e2e7492a_groups_py":{"hash":"c42ae8099607ea2a178671d523dd42a5","index":{"url":"z_52b7be57e2e7492a_groups_py.html","file":"src/downbeat/core/groups.py","description":"","nums":{"precision":0,"n_files":1,"n_statements":22,"n_excluded":0,"n_missing":0,"n_branches":0,"n_partial_branches":0,"n_missing_branches":0}}},"z_52b7be57e2e7492a_logging_py":{"hash":"4150f065ce907ed2cc0c5ba1aaf7c7cb","index":{"url":"z_52b7be57e2e7492a_logging_py.html","file":"src/downbeat/core/logging.py","description":"","nums":{"precision":0,"n_files":1,"n_statements":24,"n_excluded":0,"n_missing":0,"n_branches":0,"n_partial_branches":0,"n_missing_branches":0}}},"z_52b7be57e2e7492a_models_py":{"hash":"14157a0f9d9a8a7de2163274a7a4fe07","index":{"url":"z_52b7be57e2e7492a_models_py.html","file":"src/downbeat/core/models.py","description":"","nums":{"precision":0,"n_files":1,"n_statements":84,"n_excluded":0,"n_missing":0,"n_branches":0,"n_partial_branches":0,"n_missing_branches":0}}},"z_52b7be57e2e7492a_paths_py":{"hash":"38df2c6f96c8bac3832f96f5e5ac5d02","index":{"url":"z_52b7be57e2e7492a_paths_py.html","file":"src/downbeat/core/paths.py","description":"","nums":{"precision":0,"n_files":1,"n_statements":17,"n_excluded":0,"n_missing":0,"n_branches":0,"n_partial_branches":0,"n_missing_branches":0}}},"z_52b7be57e2e7492a_session_py":{"hash":"78f88078e348faa3952a224052a5189f","index":{"url":"z_52b7be57e2e7492a_session_py.html","file":"src/downbeat/core/session.py","description":"","nums":{"precision":0,"n_files":1,"n_statements":82,"n_excluded":0,"n_missing":30,"n_branches":0,"n_partial_branches":0,"n_missing_branches":0}}},"z_52b7be57e2e7492a_state_py":{"hash":"1f7446090572d9a294f0d70f95c28f00","index":{"url":"z_52b7be57e2e7492a_state_py.html","file":"src/downbeat/core/state.py","description":"","nums":{"precision":0,"n_files":1,"n_statements":42,"n_excluded":0,"n_missing":9,"n_branches":0,"n_partial_branches":0,"n_missing_branches":0}}},"z_52b7be57e2e7492a_store_py":{"hash":"6c595033bcf8cbe7cb4e96e73f2fe752","index":{"url":"z_52b7be57e2e7492a_store_py.html","file":"src/downbeat/core/store.py","description":"","nums":{"precision":0,"n_files":1,"n_statements":486,"n_excluded":0,"n_missing":51,"n_branches":0,"n_partial_branches":0,"n_missing_branches":0}}},"z_52b7be57e2e7492a_watcher_py":{"hash":"7b9e94b304d7827e2684ee1bdddff55e","index":{"url":"z_52b7be57e2e7492a_watcher_py.html","file":"src/downbeat/core/watcher.py","description":"","nums":{"precision":0,"n_files":1,"n_statements":87,"n_excluded":4,"n_missing":12,"n_branches":0,"n_partial_branches":0,"n_missing_branches":0}}},"z_f7effdba90412ef5_app_py":{"hash":"847a01e2da2cee2050fdb8fc6f86d92a","index":{"url":"z_f7effdba90412ef5_app_py.html","file":"src/downbeat/tui/app.py","description":"","nums":{"precision":0,"n_files":1,"n_statements":60,"n_excluded":0,"n_missing":22,"n_branches":0,"n_partial_branches":0,"n_missing_branches":0}}},"z_f7effdba90412ef5_messages_py":{"hash":"222939c1baba9f30df1a228eb72b2451","index":{"url":"z_f7effdba90412ef5_messages_py.html","file":"src/downbeat/tui/messages.py","description":"","nums":{"precision":0,"n_files":1,"n_statements":4,"n_excluded":0,"n_missing":0,"n_branches":0,"n_partial_branches":0,"n_missing_branches":0}}},"z_d2cf86fac0d4b5bd_broadcast_status_py":{"hash":"0a7736aa46c5dfc912a94f89250b84cb","index":{"url":"z_d2cf86fac0d4b5bd_broadcast_status_py.html","file":"src/downbeat/tui/screens/broadcast_status.py","description":"","nums":{"precision":0,"n_files":1,"n_statements":20,"n_excluded":0,"n_missing":20,"n_branches":0,"n_partial_branches":0,"n_missing_branches":0}}},"z_d2cf86fac0d4b5bd_chat_py":{"hash":"aaae72becad831683160be1b01333535","index":{"url":"z_d2cf86fac0d4b5bd_chat_py.html","file":"src/downbeat/tui/screens/chat.py","description":"","nums":{"precision":0,"n_files":1,"n_statements":204,"n_excluded":0,"n_missing":69,"n_branches":0,"n_partial_branches":0,"n_missing_branches":0}}},"z_d2cf86fac0d4b5bd_help_py":{"hash":"e6ca423c4974cacccef2b2a65452ffad","index":{"url":"z_d2cf86fac0d4b5bd_help_py.html","file":"src/downbeat/tui/screens/help.py","description":"","nums":{"precision":0,"n_files":1,"n_statements":12,"n_excluded":0,"n_missing":0,"n_branches":0,"n_partial_branches":0,"n_missing_branches":0}}},"z_d2cf86fac0d4b5bd_main_py":{"hash":"be10262102867f28192bf2a766194225","index":{"url":"z_d2cf86fac0d4b5bd_main_py.html","file":"src/downbeat/tui/screens/main.py","description":"","nums":{"precision":0,"n_files":1,"n_statements":152,"n_excluded":0,"n_missing":152,"n_branches":0,"n_partial_branches":0,"n_missing_branches":0}}},"z_d2cf86fac0d4b5bd_message_detail_py":{"hash":"069578a3e8140d74d9600d927ee3e1d9","index":{"url":"z_d2cf86fac0d4b5bd_message_detail_py.html","file":"src/downbeat/tui/screens/message_detail.py","description":"","nums":{"precision":0,"n_files":1,"n_statements":113,"n_excluded":0,"n_missing":62,"n_branches":0,"n_partial_branches":0,"n_missing_branches":0}}},"z_d2cf86fac0d4b5bd_peers_py":{"hash":"5982dfe1a3528e12878c4a0380eadcdf","index":{"url":"z_d2cf86fac0d4b5bd_peers_py.html","file":"src/downbeat/tui/screens/peers.py","description":"","nums":{"precision":0,"n_files":1,"n_statements":84,"n_excluded":0,"n_missing":32,"n_branches":0,"n_partial_branches":0,"n_missing_branches":0}}},"z_d2cf86fac0d4b5bd_quarantine_py":{"hash":"b57e53e83f15ecf33987ba71dda8f942","index":{"url":"z_d2cf86fac0d4b5bd_quarantine_py.html","file":"src/downbeat/tui/screens/quarantine.py","description":"","nums":{"precision":0,"n_files":1,"n_statements":73,"n_excluded":0,"n_missing":73,"n_branches":0,"n_partial_branches":0,"n_missing_branches":0}}},"z_dfa4d9b104df20fa_add_peer_modal_py":{"hash":"e33e4285e3125395fabeaac8dbbe285a","index":{"url":"z_dfa4d9b104df20fa_add_peer_modal_py.html","file":"src/downbeat/tui/widgets/add_peer_modal.py","description":"","nums":{"precision":0,"n_files":1,"n_statements":56,"n_excluded":0,"n_missing":9,"n_branches":0,"n_partial_branches":0,"n_missing_branches":0}}},"z_dfa4d9b104df20fa_chat_composer_py":{"hash":"4dc04d105e82dbf50ac0e24da6dcb9e0","index":{"url":"z_dfa4d9b104df20fa_chat_composer_py.html","file":"src/downbeat/tui/widgets/chat_composer.py","description":"","nums":{"precision":0,"n_files":1,"n_statements":64,"n_excluded":0,"n_missing":31,"n_branches":0,"n_partial_branches":0,"n_missing_branches":0}}},"z_dfa4d9b104df20fa_chat_stream_py":{"hash":"6201e404750412f1db3d9369ffd58ca6","index":{"url":"z_dfa4d9b104df20fa_chat_stream_py.html","file":"src/downbeat/tui/widgets/chat_stream.py","description":"","nums":{"precision":0,"n_files":1,"n_statements":180,"n_excluded":0,"n_missing":26,"n_branches":0,"n_partial_branches":0,"n_missing_branches":0}}},"z_dfa4d9b104df20fa_clipboard_py":{"hash":"ff92e35ed1940eeaed6fe7c6bbac3ed9","index":{"url":"z_dfa4d9b104df20fa_clipboard_py.html","file":"src/downbeat/tui/widgets/clipboard.py","description":"","nums":{"precision":0,"n_files":1,"n_statements":25,"n_excluded":0,"n_missing":20,"n_branches":0,"n_partial_branches":0,"n_missing_branches":0}}},"z_dfa4d9b104df20fa_composer_py":{"hash":"3b6247a3f3bbb4f5a31281e7297bcb6f","index":{"url":"z_dfa4d9b104df20fa_composer_py.html","file":"src/downbeat/tui/widgets/composer.py","description":"","nums":{"precision":0,"n_files":1,"n_statements":64,"n_excluded":0,"n_missing":64,"n_branches":0,"n_partial_branches":0,"n_missing_branches":0}}},"z_dfa4d9b104df20fa_confirm_py":{"hash":"4f3b67eb8654858bc501771cdd763554","index":{"url":"z_dfa4d9b104df20fa_confirm_py.html","file":"src/downbeat/tui/widgets/confirm.py","description":"","nums":{"precision":0,"n_files":1,"n_statements":20,"n_excluded":0,"n_missing":1,"n_branches":0,"n_partial_branches":0,"n_missing_branches":0}}},"z_dfa4d9b104df20fa_edit_modal_py":{"hash":"cc3d1319f5cd505c9190dbc30bdf094a","index":{"url":"z_dfa4d9b104df20fa_edit_modal_py.html","file":"src/downbeat/tui/widgets/edit_modal.py","description":"","nums":{"precision":0,"n_files":1,"n_statements":34,"n_excluded":0,"n_missing":20,"n_branches":0,"n_partial_branches":0,"n_missing_branches":0}}},"z_dfa4d9b104df20fa_find_message_py":{"hash":"a419dec1330e0cd2aa8295c068e19117","index":{"url":"z_dfa4d9b104df20fa_find_message_py.html","file":"src/downbeat/tui/widgets/find_message.py","description":"","nums":{"precision":0,"n_files":1,"n_statements":39,"n_excluded":0,"n_missing":39,"n_branches":0,"n_partial_branches":0,"n_missing_branches":0}}},"z_dfa4d9b104df20fa_inbox_list_py":{"hash":"77d99fd19e5a8b63ea8b9848575bc6fb","index":{"url":"z_dfa4d9b104df20fa_inbox_list_py.html","file":"src/downbeat/tui/widgets/inbox_list.py","description":"","nums":{"precision":0,"n_files":1,"n_statements":47,"n_excluded":0,"n_missing":47,"n_branches":0,"n_partial_branches":0,"n_missing_branches":0}}},"z_dfa4d9b104df20fa_log_viewer_py":{"hash":"8e32a039fb3b1c615cdfe9e010ef8fd6","index":{"url":"z_dfa4d9b104df20fa_log_viewer_py.html","file":"src/downbeat/tui/widgets/log_viewer.py","description":"","nums":{"precision":0,"n_files":1,"n_statements":48,"n_excluded":0,"n_missing":14,"n_branches":0,"n_partial_branches":0,"n_missing_branches":0}}},"z_dfa4d9b104df20fa_message_view_py":{"hash":"65ed0487ae2d72d3e71b6f5943b64d57","index":{"url":"z_dfa4d9b104df20fa_message_view_py.html","file":"src/downbeat/tui/widgets/message_view.py","description":"","nums":{"precision":0,"n_files":1,"n_statements":46,"n_excluded":0,"n_missing":46,"n_branches":0,"n_partial_branches":0,"n_missing_branches":0}}},"z_dfa4d9b104df20fa_peer_admin_py":{"hash":"db08d958dbb14530b284db1a94617caa","index":{"url":"z_dfa4d9b104df20fa_peer_admin_py.html","file":"src/downbeat/tui/widgets/peer_admin.py","description":"","nums":{"precision":0,"n_files":1,"n_statements":83,"n_excluded":0,"n_missing":12,"n_branches":0,"n_partial_branches":0,"n_missing_branches":0}}},"z_dfa4d9b104df20fa_peer_list_py":{"hash":"3104c472b9022c09ff65d27e2306f9d1","index":{"url":"z_dfa4d9b104df20fa_peer_list_py.html","file":"src/downbeat/tui/widgets/peer_list.py","description":"","nums":{"precision":0,"n_files":1,"n_statements":84,"n_excluded":0,"n_missing":84,"n_branches":0,"n_partial_branches":0,"n_missing_branches":0}}},"z_dfa4d9b104df20fa_peer_tabs_py":{"hash":"ef98add91581386c8e7b70f6287678ff","index":{"url":"z_dfa4d9b104df20fa_peer_tabs_py.html","file":"src/downbeat/tui/widgets/peer_tabs.py","description":"","nums":{"precision":0,"n_files":1,"n_statements":52,"n_excluded":0,"n_missing":2,"n_branches":0,"n_partial_branches":0,"n_missing_branches":0}}},"z_dfa4d9b104df20fa_rebind_modal_py":{"hash":"36d0be30c21fbe4810369ba6a0e60443","index":{"url":"z_dfa4d9b104df20fa_rebind_modal_py.html","file":"src/downbeat/tui/widgets/rebind_modal.py","description":"","nums":{"precision":0,"n_files":1,"n_statements":33,"n_excluded":0,"n_missing":33,"n_branches":0,"n_partial_branches":0,"n_missing_branches":0}}},"z_dfa4d9b104df20fa_switch_acting_as_py":{"hash":"a03d13087b135743ebc72ff7e0575cb4","index":{"url":"z_dfa4d9b104df20fa_switch_acting_as_py.html","file":"src/downbeat/tui/widgets/switch_acting_as.py","description":"","nums":{"precision":0,"n_files":1,"n_statements":33,"n_excluded":0,"n_missing":6,"n_branches":0,"n_partial_branches":0,"n_missing_branches":0}}}}}